[
    {
        "id": "lakers-earned-20-21",
        "index": 1,
        "image": "https://media.publit.io/file/w_640/LAL/lakers_20-21-earned.jpg",
        "team": "los angeles lakers",
        "short": "lal",
        "edition": "earned",
        "year": "2018-2019",
        "favorite": null,
        "brand": "nike",
        "newest": null,
        "link": null
    },
    {
        "id": "lakers-icon-18-present",
        "index": 2,
        "image": "https://media.publit.io/file/w_640/LAL/lakers_18-present-icon.jpg",
        "team": "los angeles lakers",
        "short": "lal",
        "edition": "icon",
        "year": "2018-present",
        "favorite": null,
        "brand": "nike",
        "newest": null,
        "link": null
    },
    {
        "id": "lakers-statement-20-present",
        "index": 3,
        "image": "https://media.publit.io/file/w_640/LAL/lakers_18-20-statement.jpg",
        "team": "los angeles lakers",
        "short": "lal",
        "edition": "statement",
        "year": "2020-present",
        "favorite": null,
        "brand": "jordan",
        "newest": null,
        "link": null
    },
    {
        "id": "lakers-association-2018-present",
        "index": 4,
        "image": "https://media.publit.io/file/w_640/LAL/lakers_18-present-association.jpg",
        "team": "los angeles lakers",
        "short": "lal",
        "edition": "association",
        "year": "2018-present",
        "favorite": null,
        "brand": "nike",
        "newest": null,
        "link": null
    },
    {
        "id": "lakers-city-20-21",
        "index": 5,
        "image": "https://media.publit.io/file/w_640/LAL/lakers_20-21-city.jpg",
        "team": "los angeles lakers",
        "short": "lal",
        "edition": "city",
        "year": "2020-2021",
        "favorite": null,
        "brand": "nike",
        "newest": null,
        "link": null
    },
    {
        "id": "lakers-city-19-20",
        "index": 6,
        "image": "https://media.publit.io/file/w_640/LAL/lakers_19-20-city.jpg",
        "team": "los angeles lakers",
        "short": "lal",
        "edition": "city",
        "year": "2019-2020",
        "favorite": null,
        "brand": "nike",
        "newest": null,
        "link": null
    },
    {
        "id": "lakers-classic-20-21",
        "index": 7,
        "image": "https://media.publit.io/file/w_640/LAL/lakers_20-21-classic.jpg",
        "team": "los angeles lakers",
        "short": "lal",
        "edition": "classic",
        "year": "2020-2021",
        "favorite": null,
        "brand": "nike",
        "newest": null,
        "link": null
    },
    {
        "id": "lakers-association-2017-18",
        "index": 8,
        "image": "https://media.publit.io/file/w_640/LAL/lakers_17-18-association.jpg",
        "team": "los angeles lakers",
        "short": "lal",
        "edition": "association",
        "year": "2017-18",
        "favorite": null,
        "brand": "nike",
        "newest": null,
        "link": null
    },
    {
        "id": "lakers-statement-18-20",
        "index": 9,
        "image": "https://media.publit.io/file/w_640/LAL/lakers_20-present-statement.jpg",
        "team": "los angeles lakers",
        "short": "lal",
        "edition": "association",
        "year": "2018-2020",
        "favorite": null,
        "brand": "nike",
        "newest": null,
        "link": null
    },
    {
        "id": "lakers-statement-17-18",
        "index": 10,
        "image": "https://media.publit.io/file/w_640/LAL/lakers_17-18-statement.jpg",
        "team": "los angeles lakers",
        "short": "lal",
        "edition": "association",
        "year": "2017-2018",
        "favorite": null,
        "brand": "nike",
        "newest": null,
        "link": null
    },
    {
        "id": "lakers-city-17-18",
        "index": 11,
        "image": "https://media.publit.io/file/w_640/LAL/lakers_17-18-city.jpg",
        "team": "los angeles lakers",
        "short": "lal",
        "edition": "city",
        "year": "2017-2018",
        "favorite": null,
        "brand": "nike",
        "newest": null,
        "link": null
    },
    {
        "id": "lakers-icon-17-18",
        "index": 12,
        "image": "https://media.publit.io/file/w_640/LAL/lakers_17-18-icon.jpg",
        "team": "los angeles lakers",
        "short": "lal",
        "edition": "icon",
        "year": "2017-2018",
        "favorite": null,
        "brand": "nike",
        "newest": null,
        "link": null
    },
    {
        "id": "lakers-city-18-19",
        "index": 13,
        "image": "https://media.publit.io/file/w_640/LAL/lakers_18-19-city.jpg",
        "team": "los angeles lakers",
        "short": "lal",
        "edition": "city",
        "year": "2018-2019",
        "favorite": null,
        "brand": "nike",
        "newest": null,
        "link": null
    },
    {
        "id": "raptors-city-19-20",
        "index": 14,
        "image": "https://media.publit.io/file/w_640/TOR/raptors_19-20-city.jpg",
        "team": "toronto raptors",
        "short": "tor",
        "edition": "city",
        "year": "2019-2020",
        "favorite": null,
        "brand": "nike",
        "newest": null,
        "link": "https://www.youtube.com/"
    },
    {
        "id": "raptors-earned-18-19",
        "index": 15,
        "image": "https://media.publit.io/file/w_640/TOR/raptors_18-19-earned.jpg",
        "team": "toronto raptors",
        "short": "tor",
        "edition": "earned",
        "year": "2018-2019",
        "favorite": "yes",
        "brand": "nike",
        "newest": null,
        "link": null
    },
    {
        "id": "raptors-statement-20-present",
        "index": 16,
        "image": "https://media.publit.io/file/w_640/TOR/raptors_20-present-statement.jpg",
        "team": "toronto raptors",
        "short": "tor",
        "edition": "statement",
        "year": "2020-present",
        "favorite": null,
        "brand": "jordan",
        "newest": null,
        "link": null
    },
    {
        "id": "raptors-city-20-21",
        "index": 17,
        "image": "https://media.publit.io/file/w_640/TOR/raptors_20-21-city.jpg",
        "team": "toronto raptors",
        "short": "tor",
        "edition": "city",
        "year": "2020-2021",
        "favorite": null,
        "brand": "nike",
        "newest": null,
        "link": null
    },
    {
        "id": "raptors-classic-19-20",
        "index": 18,
        "image": "https://media.publit.io/file/w_640/TOR/raptors_19-20-classic.jpg",
        "team": "toronto raptors",
        "short": "tor",
        "edition": "classic",
        "year": "2019-2020",
        "favorite": null,
        "brand": "nike",
        "newest": null,
        "link": null
    },
    {
        "id": "raptors-association-20-present",
        "index": 19,
        "image": "https://media.publit.io/file/w_640/TOR/raptors_20-present-association.jpg",
        "team": "toronto raptors",
        "short": "tor",
        "edition": "association",
        "year": "2020-present",
        "favorite": null,
        "brand": "nike",
        "newest": null,
        "link": null
    },
    {
        "id": "raptors-earned-20-21",
        "index": 20,
        "image": "https://media.publit.io/file/w_640/TOR/raptors_20-21-earned.jpg",
        "team": "toronto raptors",
        "short": "tor",
        "edition": "earned",
        "year": "2020-2021",
        "favorite": null,
        "brand": "nike",
        "newest": null,
        "link": null
    },
    {
        "id": "raptors-icon-20-present",
        "index": 21,
        "image": "https://media.publit.io/file/w_640/TOR/raptors_20-present-icon.jpg",
        "team": "toronto raptors",
        "short": "tor",
        "edition": "icon",
        "year": "2020-present",
        "favorite": null,
        "brand": "nike",
        "newest": null,
        "link": null
    },
    {
        "id": "raptors-earned-18-19",
        "index": 22,
        "image": "https://media.publit.io/file/w_640/TOR/raptors_18-19-earned.jpg",
        "team": "toronto raptors",
        "short": "tor",
        "edition": "earned",
        "year": "2018-2019",
        "favorite": null,
        "brand": "nike",
        "newest": null,
        "link": null
    },
    {
        "id": "raptors-city-18-19",
        "index": 23,
        "image": "https://media.publit.io/file/w_640/TOR/raptors_18-19-city.jpg",
        "team": "toronto raptors",
        "short": "tor",
        "edition": "city",
        "year": "2018-2019",
        "favorite": null,
        "brand": "nike",
        "newest": null,
        "link": null
    },
    {
        "id": "raptors-city-17-18",
        "index": 24,
        "image": "https://media.publit.io/file/w_640/TOR/raptors_17-18-city.jpg",
        "team": "toronto raptors",
        "short": "tor",
        "edition": "city",
        "year": "2017-2018",
        "favorite": null,
        "brand": "nike",
        "newest": null,
        "link": null
    },
    {
        "id": "raptors-icon-17-20",
        "index": 25,
        "image": "https://media.publit.io/file/w_640/TOR/raptors_17-20-icon.jpg",
        "team": "toronto raptors",
        "short": "tor",
        "edition": "icon",
        "year": "2017-2020",
        "favorite": null,
        "brand": "nike",
        "newest": null,
        "link": null
    },
    {
        "id": "raptors-statement-17-20",
        "index": 26,
        "image": "https://media.publit.io/file/w_640/TOR/raptors_17-20-statement.jpg",
        "team": "toronto raptors",
        "short": "tor",
        "edition": "statement",
        "year": "2017-2020",
        "favorite": null,
        "brand": "nike",
        "newest": null,
        "link": null
    },
    {
        "id": "raptors-association-17-20",
        "index": 27,
        "image": "https://media.publit.io/file/w_640/TOR/raptors_17-20-association.jpg",
        "team": "toronto raptors",
        "short": "tor",
        "edition": "association",
        "year": "2017-2020",
        "favorite": null,
        "brand": "nike",
        "newest": null,
        "link": null
    },
    {
        "id": "warriors-statement-20-present",
        "index": 28,
        "image": "https://media.publit.io/file/w_640/GSW/warriors_20-present-statement.jpg",
        "team": "golden state warriors",
        "short": "gsw",
        "edition": "statement",
        "year": "2020-present",
        "favorite": null,
        "brand": "jordan",
        "newest": null,
        "link": null
    },
    {
        "id": "warriors-city-20-21",
        "index": 29,
        "image": "https://media.publit.io/file/w_640/GSW/warriors_20-21-city.jpg",
        "team": "golden state warriors",
        "short": "gsw",
        "edition": "city",
        "year": "2020-2021",
        "favorite": null,
        "brand": "nike",
        "newest": null,
        "link": null
    },
    {
        "id": "warriors-icon-19-present",
        "index": 30,
        "image": "https://media.publit.io/file/w_640/GSW/warriors_19-present-icon.jpg",
        "team": "golden state warriors",
        "short": "gsw",
        "edition": "icon",
        "year": "2019-present",
        "favorite": null,
        "brand": "nike",
        "newest": null,
        "link": null
    },
    {
        "id": "warriors-classic-20-21",
        "index": 31,
        "image": "https://media.publit.io/file/w_640/GSW/warriors_20-21-classic.jpg",
        "team": "golden state warriors",
        "short": "gsw",
        "edition": "classic",
        "year": "2020-2021",
        "favorite": null,
        "brand": "nike",
        "newest": null,
        "link": null
    },
    {
        "id": "warriors-statement-18-20",
        "index": 32,
        "image": "https://media.publit.io/file/w_640/GSW/warriors_18-20-statement.jpg",
        "team": "golden state warriors",
        "short": "gsw",
        "edition": "statement",
        "year": "2017-2020",
        "favorite": null,
        "brand": "nike",
        "newest": null,
        "link": null
    },
    {
        "id": "warriors-classic-19-20",
        "index": 33,
        "image": "https://media.publit.io/file/w_640/GSW/warriors_19-20-classic.jpg",
        "team": "golden state warriors",
        "short": "gsw",
        "edition": "classic",
        "year": "2019-2020",
        "favorite": null,
        "brand": "nike",
        "newest": null,
        "link": null
    },
    {
        "id": "warriors-city-19-20",
        "index": 34,
        "image": "https://media.publit.io/file/w_640/GSW/warriors_19-20-city.jpg",
        "team": "golden state warriors",
        "short": "gsw",
        "edition": "city",
        "year": "2019-2020",
        "favorite": null,
        "brand": "nike",
        "newest": null,
        "link": null
    },
    {
        "id": "warriors-association-19-present",
        "index": 35,
        "image": "https://media.publit.io/file/w_640/GSW/warriors_19-present-association.jpg",
        "team": "golden state warriors",
        "short": "gsw",
        "edition": "association",
        "year": "2019-present",
        "favorite": null,
        "brand": "nike",
        "newest": null,
        "link": null
    },
    {
        "id": "warriors-classic-18-19",
        "index": 36,
        "image": "https://media.publit.io/file/w_640/GSW/warriors_18-19-classic.jpg",
        "team": "golden state warriors",
        "short": "gsw",
        "edition": "classic",
        "year": "2018-2019",
        "favorite": null,
        "brand": "nike",
        "newest": null,
        "link": null
    },
    {
        "id": "warriors-city-18-19",
        "index": 37,
        "image": "https://media.publit.io/file/w_640/GSW/warriors_18-19-city.jpg",
        "team": "golden state warriors",
        "short": "gsw",
        "edition": "city",
        "year": "2018-2019",
        "favorite": "yes",
        "brand": "nike",
        "newest": null,
        "link": null
    },
    {
        "id": "warriors-icon-17-19",
        "index": 38,
        "image": "https://media.publit.io/file/w_640/GSW/warriors_17-19-icon.jpg",
        "team": "golden state warriors",
        "short": "gsw",
        "edition": "icon",
        "year": "2017-2019",
        "favorite": null,
        "brand": "nike",
        "newest": null,
        "link": null
    },
    {
        "id": "warriors-classic-17-18",
        "index": 39,
        "image": "https://media.publit.io/file/w_640/GSW/warriors_17-18-classic.jpg",
        "team": "golden state warriors",
        "short": "gsw",
        "edition": "classic",
        "year": "2017-2018",
        "favorite": null,
        "brand": "nike",
        "newest": null,
        "link": null
    },
    {
        "id": "warriors-association-17-19",
        "index": 40,
        "image": "https://media.publit.io/file/w_640/GSW/warriors_17-19-association.jpg",
        "team": "golden state warriors",
        "short": "gsw",
        "edition": "association",
        "year": "2017-2019",
        "favorite": null,
        "brand": "nike",
        "newest": null,
        "link": null
    },
    {
        "id": "warriors-city-17-18",
        "index": 41,
        "image": "https://media.publit.io/file/w_640/GSW/warriors_17-18-city.jpg",
        "team": "golden state warriors",
        "short": "gsw",
        "edition": "city",
        "year": "2017-2018",
        "favorite": "yes",
        "brand": "nike",
        "newest": null,
        "link": null
    },
    {
        "id": "knicks-statement-19-20",
        "index": 42,
        "image": "https://media.publit.io/file/w_640/NYK/knicks_statement-19-20.jpg",
        "team": "new york knicks",
        "short": "nyk",
        "edition": "statement",
        "year": "2019-2020",
        "favorite": null,
        "brand": "nike",
        "newest": null,
        "link": null
    },
    {
        "id": "knicks-city-17-18",
        "index": 43,
        "image": "https://media.publit.io/file/w_640/NYK/knicks_city-17-18.jpg",
        "team": "new york knicks",
        "short": "nyk",
        "edition": "city",
        "year": "2018-2019",
        "favorite": "yes",
        "brand": "nike",
        "newest": null,
        "link": null
    },
    {
        "id": "knicks-association-17-present",
        "index": 44,
        "image": "https://media.publit.io/file/w_640/NYK/knicks_association-17-present.jpg",
        "team": "new york knicks",
        "short": "nyk",
        "edition": "association",
        "year": "2017-present",
        "favorite": null,
        "brand": "nike",
        "newest": null,
        "link": null
    },
    {
        "id": "knicks-icon-17-present",
        "index": 45,
        "image": "https://media.publit.io/file/w_640/NYK/knicks_icon-17-present.jpg",
        "team": "new york knicks",
        "short": "nyk",
        "edition": "icon",
        "year": "2017-present",
        "favorite": null,
        "brand": "nike",
        "newest": null,
        "link": null
    },
    {
        "id": "knicks-city-18-20",
        "index": 46,
        "image": "https://media.publit.io/file/w_640/NYK/knicks_city-18-20.jpg",
        "team": "new york knicks",
        "short": "nyk",
        "edition": "city",
        "year": "2018-2020",
        "favorite": null,
        "brand": "nike",
        "newest": null,
        "link": null
    },
    {
        "id": "knicks-statement-20-present",
        "index": 47,
        "image": "https://media.publit.io/file/w_640/NYK/knicks_statement-20-present.jpg",
        "team": "new york knicks",
        "short": "nyk",
        "edition": "city",
        "year": "2020-present",
        "favorite": null,
        "brand": "jordan",
        "newest": null,
        "link": null
    },
    {
        "id": "knicks-statement-17-19",
        "index": 48,
        "image": "https://media.publit.io/file/w_640/NYK/knicks_statement-17-19.jpg",
        "team": "new york knicks",
        "short": "nyk",
        "edition": "statement",
        "year": "2017-2019",
        "favorite": null,
        "brand": "nike",
        "newest": null,
        "link": null
    },
    {
        "id": "knicks-city-20-21",
        "index": 49,
        "image": "https://media.publit.io/file/w_640/NYK/knicks_city-20-21.jpg",
        "team": "new york knicks",
        "short": "nyk",
        "edition": "city",
        "year": "2020-2021",
        "favorite": null,
        "brand": "nike",
        "newest": null,
        "link": null
    },
    {
        "id": "thunder-statement-19-20",
        "index": 50,
        "image": "https://media.publit.io/file/w_640/OKC/thunder_statement-19-20.jpg",
        "team": "oklahoma city thunder",
        "short": "okc",
        "edition": "statement",
        "year": "2019-2020",
        "favorite": null,
        "brand": "nike",
        "newest": null,
        "link": null
    },
    {
        "id": "thunder-icon-19-present",
        "index": 51,
        "image": "https://media.publit.io/file/w_640/OKC/thunder_icon-19-present.jpg",
        "team": "oklahoma city thunder",
        "short": "okc",
        "edition": "icon",
        "year": "2019-present",
        "favorite": null,
        "brand": "nike",
        "newest": null,
        "link": null
    },
    {
        "id": "thunder-statement-17-19",
        "index": 52,
        "image": "https://media.publit.io/file/w_640/OKC/thunder_statement-17-19.jpg",
        "team": "oklahoma city thunder",
        "short": "okc",
        "edition": "statement",
        "year": "2017-2019",
        "favorite": null,
        "brand": "nike",
        "newest": null,
        "link": null
    },
    {
        "id": "thunder-statement-20-present",
        "index": 53,
        "image": "https://media.publit.io/file/w_640/OKC/thunder_statement-20-present.jpg",
        "team": "oklahoma city thunder",
        "short": "okc",
        "edition": "statement",
        "year": "2020-present",
        "favorite": null,
        "brand": "jordan",
        "newest": null,
        "link": null
    },
    {
        "id": "thunder-icon-17-19",
        "index": 54,
        "image": "https://media.publit.io/file/w_640/OKC/thunder_icon-17-19.jpg",
        "team": "oklahoma city thunder",
        "short": "okc",
        "edition": "icon",
        "year": "2017-2019",
        "favorite": null,
        "brand": "nike",
        "newest": null,
        "link": null
    },
    {
        "id": "thunder-city-17-18",
        "index": 55,
        "image": "https://media.publit.io/file/w_640/OKC/thunder_city-17-18.jpg",
        "team": "oklahoma city thunder",
        "short": "okc",
        "edition": "city",
        "year": "2017-2018",
        "favorite": null,
        "brand": "nike",
        "newest": null,
        "link": null
    },
    {
        "id": "thunder-city-19-20",
        "index": 56,
        "image": "https://media.publit.io/file/w_640/OKC/thunder_city-19-20.jpg",
        "team": "oklahoma city thunder",
        "short": "okc",
        "edition": "city",
        "year": "2019-2020",
        "favorite": null,
        "brand": "nike",
        "newest": null,
        "link": null
    },
    {
        "id": "thunder-city-18-19",
        "index": 57,
        "image": "https://media.publit.io/file/w_640/OKC/thunder_city-18-19.jpg",
        "team": "oklahoma city thunder",
        "short": "okc",
        "edition": "city",
        "year": "2018-2019",
        "favorite": "yes",
        "brand": "nike",
        "newest": null,
        "link": null
    },
    {
        "id": "thunder-association-19-present",
        "index": 58,
        "image": "https://media.publit.io/file/w_640/OKC/thunder_association-19-present.jpg",
        "team": "oklahoma city thunder",
        "short": "okc",
        "edition": "city",
        "year": "2019-present",
        "favorite": null,
        "brand": "nike",
        "newest": null,
        "link": null
    },
    {
        "id": "thunder-earned-18-19",
        "index": 59,
        "image": "https://media.publit.io/file/w_640/OKC/thunder_earned-18-19.jpg",
        "team": "oklahoma city thunder",
        "short": "okc",
        "edition": "earned",
        "year": "2018-19",
        "favorite": null,
        "brand": "nike",
        "newest": null,
        "link": null
    },
    {
        "id": "thunder-city-20-21",
        "index": 60,
        "image": "https://media.publit.io/file/w_640/OKC/thunder_city-20-21.jpg",
        "team": "oklahoma city thunder",
        "short": "okc",
        "edition": "city",
        "year": "2020-2021",
        "favorite": null,
        "brand": "nike",
        "newest": null,
        "link": null
    },
    {
        "id": "thunder-association-17-19",
        "index": 61,
        "image": "https://media.publit.io/file/w_640/OKC/thunder_association-17-19.jpg",
        "team": "oklahoma city thunder",
        "short": "okc",
        "edition": "association",
        "year": "2017-2019",
        "favorite": null,
        "brand": "nike",
        "newest": null,
        "link": null
    },
    {
        "id": "thunder-earned-20-21",
        "index": 62,
        "image": "https://media.publit.io/file/w_640/OKC/thunder_earned-20-21.jpg",
        "team": "oklahoma city thunder",
        "short": "okc",
        "edition": "earned",
        "year": "2020-2021",
        "favorite": null,
        "brand": "nike",
        "newest": null,
        "link": null
    },
    {
        "id": "bulls-association-17-present",
        "index": 63,
        "image": "https://media.publit.io/file/w_640/CHI/bulls_association-17-present.jpg",
        "team": "chicago bulls",
        "short": "chi",
        "edition": "association",
        "year": "2017-present",
        "favorite": null,
        "brand": "nike",
        "newest": null,
        "link": null
    },
    {
        "id": "bulls-statement-20-present",
        "index": 64,
        "image": "https://media.publit.io/file/w_640/CHI/bulls_statement-20-present.jpg",
        "team": "chicago bulls",
        "short": "chi",
        "edition": "statement",
        "year": "2020-present",
        "favorite": null,
        "brand": "jordan",
        "newest": null,
        "link": null
    },
    {
        "id": "bulls-city-19-20",
        "index": 65,
        "image": "https://media.publit.io/file/w_640/CHI/bulls_city-19-20.jpg",
        "team": "chicago bulls",
        "short": "chi",
        "edition": "city",
        "year": "2019-2020",
        "favorite": null,
        "brand": "nike",
        "newest": null,
        "link": null
    },
    {
        "id": "bulls-city-20-21",
        "index": 66,
        "image": "https://media.publit.io/file/w_640/CHI/bulls_city-20-21.jpg",
        "team": "chicago bulls",
        "short": "chi",
        "edition": "city",
        "year": "2020-2021",
        "favorite": null,
        "brand": "nike",
        "newest": null,
        "link": null
    },
    {
        "id": "bulls-statement-19-20",
        "index": 67,
        "image": "https://media.publit.io/file/w_640/CHI/bulls_statement-19-20.jpg",
        "team": "chicago bulls",
        "short": "chi",
        "edition": "statement",
        "year": "2019-2020",
        "favorite": null,
        "brand": "nike",
        "newest": null,
        "link": null
    },
    {
        "id": "bulls-icon-17-present",
        "index": 68,
        "image": "https://media.publit.io/file/w_640/CHI/bulls_icon-17-present.jpg",
        "team": "chicago bulls",
        "short": "chi",
        "edition": "icon",
        "year": "2017-present",
        "favorite": null,
        "brand": "nike",
        "newest": null,
        "link": null
    },
    {
        "id": "bulls-city-18-19",
        "index": 69,
        "image": "https://media.publit.io/file/w_640/CHI/bulls_city-18-19.jpg",
        "team": "chicago bulls",
        "short": "chi",
        "edition": "city",
        "year": "2018-2019",
        "favorite": null,
        "brand": "nike",
        "newest": null,
        "link": null
    },
    {
        "id": "bulls-city-17-18",
        "index": 70,
        "image": "https://media.publit.io/file/w_640/CHI/bulls_city-17-18.jpg",
        "team": "chicago bulls",
        "short": "chi",
        "edition": "city",
        "year": "2017-2018",
        "favorite": null,
        "brand": "nike",
        "newest": null,
        "link": null
    },
    {
        "id": "bulls-statement-17-19",
        "index": 71,
        "image": "https://media.publit.io/file/w_640/CHI/bulls_statement-17-19.jpg",
        "team": "chicago bulls",
        "short": "chi",
        "edition": "statement",
        "year": "2017-209",
        "favorite": null,
        "brand": "nike",
        "newest": null,
        "link": null
    },
    {
        "id": "pelicans-statement-20-present",
        "index": 72,
        "image": "https://media.publit.io/file/w_640/NOP/pelicans_statement-20-present.jpg",
        "team": "new orleands pelicans",
        "short": "nop",
        "edition": "statement",
        "year": "2020-present",
        "favorite": null,
        "brand": "jordan",
        "newest": null,
        "link": null
    },
    {
        "id": "pelicans-earned-18-19",
        "index": 73,
        "image": "https://media.publit.io/file/w_640/NOP/pelicans_earned-18-19.jpg",
        "team": "new orleands pelicans",
        "short": "nop",
        "edition": "earned",
        "year": "2018-2019",
        "favorite": null,
        "brand": "nike",
        "newest": null,
        "link": null
    },
    {
        "id": "pelicans-icon-17-present",
        "index": 74,
        "image": "https://media.publit.io/file/w_640/NOP/pelicans_icon-17-present.jpg",
        "team": "new orleands pelicans",
        "short": "nop",
        "edition": "icon",
        "year": "2017-present",
        "favorite": null,
        "brand": "nike",
        "newest": null,
        "link": null
    },
    {
        "id": "pelicans-icon-20-21",
        "index": 75,
        "image": "https://media.publit.io/file/w_640/NOP/pelicans_city-20-21.jpg",
        "team": "new orleands pelicans",
        "short": "nop",
        "edition": "city",
        "year": "2020-2021",
        "favorite": null,
        "brand": "nike",
        "newest": null,
        "link": null
    },
    {
        "id": "pelicans-association-17-present",
        "index": 76,
        "image": "https://media.publit.io/file/w_640/NOP/pelicans_association-17-present.jpg",
        "team": "new orleands pelicans",
        "short": "nop",
        "edition": "association",
        "year": "2017-present",
        "favorite": null,
        "brand": "nike",
        "newest": null,
        "link": null
    },
    {
        "id": "pelicans-city-17-18",
        "index": 77,
        "image": "https://media.publit.io/file/w_640/NOP/pelicans_city-17-18.jpg",
        "team": "new orleands pelicans",
        "short": "nop",
        "edition": "city",
        "year": "2017-2018",
        "favorite": "yes",
        "brand": "nike",
        "newest": null,
        "link": null
    },
    {
        "id": "pelicans-statement-17-20",
        "index": 78,
        "image": "https://media.publit.io/file/w_640/NOP/pelicans_statement-17-20.jpg",
        "team": "new orleands pelicans",
        "short": "nop",
        "edition": "statement",
        "year": "2017-2020",
        "favorite": null,
        "brand": "nike",
        "newest": null,
        "link": null
    },
    {
        "id": "pelicans-city-18-19",
        "index": 79,
        "image": "https://media.publit.io/file/w_640/NOP/pelicans_city-18-20.jpg",
        "team": "new orleands pelicans",
        "short": "nop",
        "edition": "city",
        "year": "2018-2019",
        "favorite": null,
        "brand": "nike",
        "newest": null,
        "link": null
    }


]
